weather/__init__.py
weather/main.py
weather_ch-0.0.4.dist-info/LICENSE
weather_ch-0.0.4.dist-info/METADATA
weather_ch-0.0.4.dist-info/WHEEL
weather_ch-0.0.4.dist-info/top_level.txt
weather_ch-0.0.4.dist-info/RECORD
