Metadata-Version: 2.1
Name: weather-ch
Version: 0.0.4
Summary: Python library for weather information.
Home-page: https://github.com/calebyhan/weather_library
Author: Caleb Han
Author-email: calebhantech@gmail.com
License: MIT
Classifier: License :: OSI Approved :: MIT License
Classifier: Programming Language :: Python :: 3
Classifier: Operating System :: OS Independent
License-File: LICENSE
